setuptools_wrapper/__init__.py
setuptools_wrapper/dev_requirements.txt
setuptools_wrapper/py.typed
setuptools_wrapper/requirements.txt
setuptools_wrapper/setup.py
setuptools_wrapper/data/empty.txt
setuptools_wrapper-0.2.9.dist-info/licenses/LICENSE
setuptools_wrapper-0.2.9.dist-info/METADATA
setuptools_wrapper-0.2.9.dist-info/WHEEL
setuptools_wrapper-0.2.9.dist-info/top_level.txt
setuptools_wrapper-0.2.9.dist-info/RECORD
